README.rst
setup.py
mpcs/__init__.py
mpcs/mpcs.py
mpcs.egg-info/PKG-INFO
mpcs.egg-info/SOURCES.txt
mpcs.egg-info/dependency_links.txt
mpcs.egg-info/not-zip-safe
mpcs.egg-info/requires.txt
mpcs.egg-info/top_level.txt