Metadata-Version: 1.0
Name: mpcs
Version: 1.0.3
Summary: This app simulates an MPC compute call and creates a z-score file.
Home-page: https://github.com/FNNDSC/pl-mpcs
Author: Rudolph Pienaar
Author-email: rudolph.pienaar@gmail.com
License: MIT
Platform: UNKNOWN
